fivalid
