Metadata-Version: 1.1
Name: fivalid
Version: 0.2.5
Summary: Lightweight field data validator.
Home-page: https://github.com/AkiraKito/fivalid
Author: Akira Kito
Author-email: UNKNOWN
License: BSD
Platform: any
Classifier: Development Status :: 4 - Beta
Classifier: Intended Audience :: Developers
Classifier: License :: OSI Approved :: BSD License
Classifier: Operating System :: OS Independent
Classifier: Programming Language :: Python :: 2.5
Classifier: Topic :: Software Development :: Libraries :: Python Modules
